hip_attn/__init__.py
hip_attn/models/__init__.py
hip_attn/models/modeling_llama.py
hip_attn/models/gemma/__init__.py
hip_attn/models/gemma/modeling_gemma2.py
hip_attn/models/llava/__init__.py
hip_attn/models/llava/builder.py
hip_attn/models/llava/configuration_llava.py
hip_attn/models/llava/llava_llama.py
hip_attn/models/llava/modeling_llava.py
hip_attn/models/llava/processing_llava.py
hip_attn/models/qwen/__init__.py
hip_attn/models/qwen/modeling_qwen2.py
hip_attn/utils/__init__.py
hip_attn/utils/attention.py
hip_attn/utils/attention_norm.py
hip_attn/utils/attn_l1_loss.py
hip_attn/utils/benchmarking.py
hip_attn/utils/memory_efficient_llm_ce.py
hip_attn/utils/new_block_sparse.py
hip_attn/utils/rope.py
hip_attn/utils/rotate.py
hip_attn/utils/triton_argsort.py
hip_attn/v1_0/__init__.py
hip_attn/v1_0/attention1.py
hip_attn/v1_0/attention1_block_gpu.py
hip_attn/v1_0/attention1_gpu.py
hip_attn/v1_0/attention1_block_gpu_kernel/__init__.py
hip_attn/v1_0/attention1_block_gpu_kernel/calc_prob_return_context.py
hip_attn/v1_0/attention1_block_gpu_kernel/calc_score_return_prob.py
hip_attn/v1_0/attention1_block_gpu_kernel/masking_iteration.py
hip_attn/v1_0/attention1_block_gpu_kernel/paged_cache_vllm_compat.py
hip_attn/v1_0/attention1_block_gpu_kernel/safe_indices.py
hip_attn/v1_1/__init__.py
hip_attn/v1_1/attention2_draft.py
hip_attn/v1_1/attention2_draft_causal_batch.py
hip_attn/v1_1/attention2_draft_causal_batch_gpu.py
hip_attn/v1_1/attention2_draft_causal_batch_gpu_fused.py
hip_attn/v1_1/attention2_draft_causal_batch_gpu_fused_vec.py
hip_attn/v1_1/attention2_draft_prefetch.py
hip_attn/v1_1/attention2_draft_sampling.py
hip_attn/v1_1/attention2_draft_sampling_extend.py
hip_attn/v1_1/offload_runner/__init__.py
hip_attn/v1_1/offload_runner/cache_policy.py
hip_attn/v1_1/offload_runner/llama_model.py
hip_attn/v1_1/offload_runner/offload_runner.py
hip_attn/v1_1/offload_runner/tensor_from_pointer.cpp
hip_attn/v1_1/offload_runner/tensor_from_pointer.py
hip_attn/v1_2/__init__.py
hip_attn-1.2.9.dist-info/licenses/LICENSE.md
hip_attn-1.2.9.dist-info/METADATA
hip_attn-1.2.9.dist-info/WHEEL
hip_attn-1.2.9.dist-info/top_level.txt
hip_attn-1.2.9.dist-info/RECORD
