Metadata-Version: 2.4
Name: hip-attn
Version: 1.2.9
Summary: HiP Attention
Author-email: "DeepAuto.ai" <contact@deepauto.ai>, Heejun Lee <gmlwns5176@gmail.com>, Geon Park <mujjingun@gmail.com>, Bumsik Kim <k.bumsik@gmail.com>
License-Expression: LicenseRef-FSL-1.1-MIT
Project-URL: Homepage, https://github.com/DeepAuto-AI/hip-attention
Project-URL: Repository, https://github.com/DeepAuto-AI/hip-attention
Project-URL: Issues, https://github.com/DeepAuto-AI/hip-attention/issues
Classifier: Topic :: Scientific/Engineering :: Artificial Intelligence
Classifier: Environment :: GPU
Classifier: Environment :: GPU :: NVIDIA CUDA :: 12
Requires-Python: <3.13,>=3.10
License-File: LICENSE.md
Requires-Dist: torch
Requires-Dist: triton
Requires-Dist: setuptools>=80.9.0
Requires-Dist: numba
Requires-Dist: performer_pytorch
Requires-Dist: peft
Requires-Dist: seaborn
Requires-Dist: sympy
Requires-Dist: bitsandbytes
Requires-Dist: tilelang
Requires-Dist: cupy-cuda12x
Requires-Dist: nvtx
Requires-Dist: opencv-python-headless>=4.11.0.86
Provides-Extra: sglang
Requires-Dist: sgl-kernel; extra == "sglang"
Requires-Dist: flashinfer-python; extra == "sglang"
Requires-Dist: flash-attn>=2.8.3; extra == "sglang"
Requires-Dist: sglang[all]; extra == "sglang"
Dynamic: license-file
